nanohakase/__init__.py
nanohakase/rpc.py
nanohakase/util.py
nanohakase/wallet.py
nanohakase-0.0.5.dist-info/LICENSE
nanohakase-0.0.5.dist-info/METADATA
nanohakase-0.0.5.dist-info/WHEEL
nanohakase-0.0.5.dist-info/top_level.txt
nanohakase-0.0.5.dist-info/RECORD
