Metadata-Version: 2.1
Name: nanohakase
Version: 0.0.5
Summary: A python library to simplify sending and receiving Nano. Also a RPC wrapper. Self fork of bananopie.
Home-page: https://github.com/jetstream0/nanopie
Author: John Doe
Author-email: prussia@prussia.dev
License: MIT
Classifier: Programming Language :: Python :: 3
Classifier: License :: OSI Approved :: MIT License
Classifier: Operating System :: OS Independent
Requires-Python: >=3.5
License-File: LICENSE
Requires-Dist: requests
Requires-Dist: ed25519-blake2b
